chlorophyll/__init__.py
chlorophyll/codeview.py
chlorophyll/schemeparser.py
chlorophyll/colorschemes/ayu-dark.toml
chlorophyll/colorschemes/ayu-light.toml
chlorophyll/colorschemes/dracula.toml
chlorophyll/colorschemes/mariana.toml
chlorophyll/colorschemes/monokai.toml
chlorophyll-0.1.1.dist-info/LICENSE
chlorophyll-0.1.1.dist-info/METADATA
chlorophyll-0.1.1.dist-info/WHEEL
chlorophyll-0.1.1.dist-info/top_level.txt
chlorophyll-0.1.1.dist-info/RECORD
