Metadata-Version: 2.1
Name: chlorophyll
Version: 0.1.1
Summary: A module that fills your code with color - syntax highlighted text box widget for Tkinter.
Home-page: https://gitlab.com/rdbende/chlorophyll
Author: rdbende
Author-email: rdbende@gmail.com
License: MIT license
Platform: UNKNOWN
Classifier: Development Status :: 3 - Alpha
Classifier: Intended Audience :: Developers
Classifier: License :: OSI Approved :: MIT License
Classifier: Operating System :: OS Independent
Classifier: Programming Language :: Python :: 3 :: Only
Classifier: Programming Language :: Python :: 3.7
Classifier: Programming Language :: Python :: 3.8
Classifier: Programming Language :: Python :: 3.9
Classifier: Programming Language :: Python :: 3.10
Classifier: Typing :: Typed
Requires-Python: >=3.7
Requires-Dist: pygments
Requires-Dist: toml
